<Ui xmlns="http://www.blizzard.com/wow/ui/" xmlns:xsi="http://www.w3.org/2001/XMLSchema-instance"
    xsi:schemaLocation="http://www.blizzard.com/wow/ui/ https://raw.githubusercontent.com/Meorawr/wow-ui-schema/main/UI.xsd">
    <Font name="DatamineCleanFontBase" virtual="true"
        font="Interface/AddOns/Datamine/Assets/Roboto-Regular.ttf" height="15">
        <Color r="1" g="1" b="1" />
    </Font>

    <Font name="DatamineCleanFont" inherits="DatamineCleanFontBase">
        <Shadow x="1.5" y="-1.5" />
    </Font>
    <Font name="DatamineCleanFontNoShadow" inherits="DatamineCleanFontBase" />

    <Font name="DatamineCleanFontSmall" inherits="DatamineCleanFont" height="10" />
    <Font name="DatamineCleanFontSmallNoShadow" inherits="DatamineCleanFontNoShadow"
        height="10" />

    <Font name="DatamineCleanFontLabelSmall" inherits="DatamineCleanFont" height="5" />
</Ui>